anomed_anonymizer/__init__.py
anomed_anonymizer/anonymizer.py
anomed_anonymizer/anonymizer_server.py
anomed_anonymizer-0.0.22.dist-info/METADATA
anomed_anonymizer-0.0.22.dist-info/WHEEL
anomed_anonymizer-0.0.22.dist-info/licenses/LICENSE
anomed_anonymizer-0.0.22.dist-info/RECORD
