Metadata-Version: 2.4
Name: anomed-anonymizer
Version: 0.0.22
Summary: A library aiding to create anonymizers (privacy preserving machine learning models) for the AnoMed competition platform.
Project-URL: documentation, https://anomed-anonymizer.readthedocs.io/en/latest/
Project-URL: source, https://github.com/ypotdevin/anomed_anonymizer
Author-email: Yannik Potdevin <ypo.uzl@proton.me>
Maintainer-email: Yannik Potdevin <ypo.uzl@proton.me>
License: MIT License
License-File: LICENSE
Classifier: Development Status :: 1 - Planning
Classifier: Intended Audience :: Developers
Requires-Python: >=3.10
Requires-Dist: anomed-challenge
Requires-Dist: anomed-utils
Requires-Dist: falcon~=4.0
Requires-Dist: numpy~=1.26
Requires-Dist: pandas~=2.2
Requires-Dist: requests~=2.32
Provides-Extra: dev
Requires-Dist: ruff~=0.7; extra == 'dev'
Provides-Extra: test
Requires-Dist: coverage~=7.6; extra == 'test'
Requires-Dist: pytest-cov~=6.0; extra == 'test'
Requires-Dist: pytest-mock~=3.14; extra == 'test'
Requires-Dist: pytest~=8.3; extra == 'test'
Requires-Dist: scikit-learn~=1.6; extra == 'test'
Provides-Extra: tfkeras
Requires-Dist: tf-keras~=2.18; extra == 'tfkeras'
Provides-Extra: torch
Requires-Dist: torch~=2.6; extra == 'torch'
